paceval.py
paceval-4.25.4.dist-info/LICENSE
paceval-4.25.4.dist-info/METADATA
paceval-4.25.4.dist-info/WHEEL
paceval-4.25.4.dist-info/top_level.txt
paceval-4.25.4.dist-info/RECORD
